{
  "schemaVersion": "1.0",
  "updated": "2026-05-28T13:51:42.791Z",
  "articles": [
    {
      "slug": "ai-thinking-trap",
      "title": "AI 时代的思考陷阱：你是在思考，还是在被思考？",
      "date": "2026-05-28",
      "tags": [
        "AI哲学"
      ],
      "excerpt": "",
      "readingTime": "1min"
    },
    {
      "slug": "product-sense-vs-prompt",
      "title": "Prompt 写得好 ≠ 产品感好",
      "date": "2026-05-28",
      "tags": [
        "AI产品"
      ],
      "excerpt": "",
      "readingTime": "1min"
    },
    {
      "slug": "developer-fomo-2026",
      "title": "2026 程序员生存指南：不焦虑的活法",
      "date": "2026-05-28",
      "tags": [
        "AI杂谈"
      ],
      "excerpt": "",
      "readingTime": "1min"
    }
  ]
}